{
	"_version": "1.1.0",
	"resources": [
		{
			"name": "Search.less",
			"size": 15743,
			"designtime": true,
			"theme": "base"
		},
		{
			"name": "SearchBarChart.less",
			"size": 813,
			"designtime": true,
			"theme": "base"
		},
		{
			"name": "SearchFacet.less",
			"size": 2296,
			"designtime": true,
			"theme": "base"
		},
		{
			"name": "SearchFacetDialog.less",
			"size": 5314,
			"designtime": true,
			"theme": "base"
		},
		{
			"name": "SearchFacetTabBar.less",
			"size": 1035,
			"designtime": true,
			"theme": "base"
		},
		{
			"name": "SearchFieldGroup.less",
			"size": 5585,
			"designtime": true,
			"theme": "base"
		},
		{
			"name": "SearchPieChart.less",
			"size": 742,
			"designtime": true,
			"theme": "base"
		},
		{
			"name": "SearchResultGridTile.less",
			"size": 182,
			"designtime": true,
			"theme": "base"
		},
		{
			"name": "SearchResultListItem.less",
			"size": 28840,
			"designtime": true,
			"theme": "base"
		},
		{
			"name": "SearchTileContainer.less",
			"size": 3320,
			"designtime": true,
			"theme": "base"
		},
		{
			"name": "library-RTL.css",
			"size": 64939,
			"theme": "base"
		},
		{
			"name": "library-parameters.json",
			"module": "sap/esh/search/ui/themes/base/library-parameters.json",
			"size": 361,
			"theme": "base"
		},
		{
			"name": "library.css",
			"size": 64932,
			"theme": "base"
		},
		{
			"name": "library.source.less",
			"size": 577,
			"designtime": true,
			"theme": "base"
		},
		{
			"name": "resources.json",
			"size": 1531
		}
	]
}