{
	"_version": "1.1.0",
	"resources": [
		{
			"name": "Component-dbg.js",
			"module": "sap/fe/ariba/ListReport/Component.js",
			"size": 1975,
			"isDebug": true,
			"required": [
				"sap/fe/base/ClassSupport.js",
				"sap/fe/templates/ListReport/Component.js",
				"sap/m/library.js"
			]
		},
		{
			"name": "Component-dbg.js.map",
			"size": 2091,
			"isDebug": true
		},
		{
			"name": "Component.js",
			"module": "sap/fe/ariba/ListReport/Component.js",
			"size": 1046,
			"required": [
				"sap/fe/base/ClassSupport.js",
				"sap/fe/templates/ListReport/Component.js",
				"sap/m/library.js"
			]
		},
		{
			"name": "Component.js.map",
			"size": 1785,
			"isDebug": true
		},
		{
			"name": "Component.ts",
			"size": 872
		},
		{
			"name": "ListReportController-dbg.controller.js",
			"module": "sap/fe/ariba/ListReport/ListReportController.controller.js",
			"size": 1494,
			"isDebug": true,
			"required": [
				"sap/fe/base/ClassSupport.js",
				"sap/fe/templates/ListReport/ListReportController.controller.js"
			]
		},
		{
			"name": "ListReportController-dbg.controller.js.map",
			"size": 1308,
			"isDebug": true
		},
		{
			"name": "ListReportController.controller.js",
			"module": "sap/fe/ariba/ListReport/ListReportController.controller.js",
			"size": 775,
			"required": [
				"sap/fe/base/ClassSupport.js",
				"sap/fe/templates/ListReport/ListReportController.controller.js"
			]
		},
		{
			"name": "ListReportController.controller.js.map",
			"size": 1150,
			"isDebug": true
		},
		{
			"name": "ListReportController.controller.ts",
			"size": 531
		},
		{
			"name": "manifest.json",
			"module": "sap/fe/ariba/ListReport/manifest.json",
			"size": 385
		},
		{
			"name": "resources.json",
			"size": 1750
		}
	]
}