{
	"_version": "1.1.0",
	"resources": [
		{
			"name": "Component-dbg.js",
			"module": "sap/fe/core/fpm/Component.js",
			"size": 5007,
			"isDebug": true,
			"required": [
				"sap/f/library.js",
				"sap/fe/base/ClassSupport.js",
				"sap/fe/core/TemplateComponent.js",
				"sap/fe/macros/library.js",
				"sap/m/library.js",
				"sap/ui/core/library.js",
				"sap/ui/fl/library.js",
				"sap/ui/layout/library.js",
				"sap/ui/mdc/library.js"
			]
		},
		{
			"name": "Component-dbg.js.map",
			"size": 4767,
			"isDebug": true
		},
		{
			"name": "Component.js",
			"module": "sap/fe/core/fpm/Component.js",
			"size": 2255,
			"required": [
				"sap/f/library.js",
				"sap/fe/base/ClassSupport.js",
				"sap/fe/core/TemplateComponent.js",
				"sap/fe/macros/library.js",
				"sap/m/library.js",
				"sap/ui/core/library.js",
				"sap/ui/fl/library.js",
				"sap/ui/layout/library.js",
				"sap/ui/mdc/library.js"
			]
		},
		{
			"name": "Component.js.map",
			"size": 4026,
			"isDebug": true
		},
		{
			"name": "Component.ts",
			"size": 2223
		},
		{
			"name": "manifest.json",
			"module": "sap/fe/core/fpm/manifest.json",
			"size": 1182
		},
		{
			"name": "resources.json",
			"size": 1214
		}
	]
}